LICENSE
README.md
setup.py
./fast_ulid/ULID.cpp
fast_ulid/ULID.cpp
fast_ulid/ULID_above_37.cpp
fast_ulid/ULID_below_36.cpp
fast_ulid/__init__.pyi
fast_ulid/py.typed
fast_ulid.egg-info/PKG-INFO
fast_ulid.egg-info/SOURCES.txt
fast_ulid.egg-info/dependency_links.txt
fast_ulid.egg-info/top_level.txt
tests/test.py